{
  "_format": "hh-sol-cache-2",
  "files": {
    "C:\\Users\\Dexter\\projects\\contract-deploy-test\\contracts\\FirstContract.sol": {
      "lastModificationDate": 1691202408088,
      "contentHash": "00465c6c4173cce19ad7c342da81a658",
      "sourceName": "contracts/FirstContract.sol",
      "solcConfig": {
        "version": "0.8.10",
        "settings": {
          "optimizer": {
            "enabled": false,
            "runs": 200
          },
          "outputSelection": {
            "*": {
              "*": [
                "abi",
                "evm.bytecode",
                "evm.deployedBytecode",
                "evm.methodIdentifiers",
                "metadata"
              ],
              "": [
                "ast"
              ]
            }
          }
        }
      },
      "imports": [],
      "versionPragmas": [
        "^0.8.10"
      ],
      "artifacts": [
        "HelloWorld"
      ]
    }
  }
}
